LICENSE.txt
MANIFEST.in
README.rst
setup.py
version.txt
docs/AUTHORS.txt
docs/HISTORY.txt
docs/INSTALL.rst
docs/LICENSE.GPL
vnccollab/__init__.py
vnccollab.portal.egg-info/PKG-INFO
vnccollab.portal.egg-info/SOURCES.txt
vnccollab.portal.egg-info/dependency_links.txt
vnccollab.portal.egg-info/entry_points.txt
vnccollab.portal.egg-info/namespace_packages.txt
vnccollab.portal.egg-info/not-zip-safe
vnccollab.portal.egg-info/requires.txt
vnccollab.portal.egg-info/top_level.txt
vnccollab/portal/__init__.py
vnccollab/portal/configure.zcml
vnccollab/portal/overrides.zcml
vnccollab/portal/setuphandlers.py
vnccollab/portal/testing.py
vnccollab/portal/profiles/default/cmfnotification.xml
vnccollab/portal/profiles/default/metadata.xml
vnccollab/portal/profiles/default/vnccollab.portal.txt
vnccollab/portal/tests/__init__.py
vnccollab/portal/tests/robot_test.txt
vnccollab/portal/tests/test_basic.py
vnccollab/portal/tests/test_robot.py
vnccollab/portal/upgrades/__init__.py
vnccollab/portal/upgrades/configure.zcml