Metadata-Version: 1.1
Name: vnccollab.portal
Version: 1.0.0
Summary: VNC Collaboration Portal
Home-page: https://github.com/vnc-biz/vnccollab.portal
Author: Jose Dinuncio
Author-email: jose.dinuncio@vnc.biz
License: gpl
Platform: UNKNOWN
Classifier: Environment :: Web Environment
Classifier: Framework :: Plone
Classifier: Operating System :: OS Independent
Classifier: Programming Language :: Python
Classifier: Programming Language :: Python :: 2.6
Classifier: Topic :: Software Development :: Libraries :: Python Modules
